setup.py
ProxmoxDriver.egg-info/PKG-INFO
ProxmoxDriver.egg-info/SOURCES.txt
ProxmoxDriver.egg-info/dependency_links.txt
ProxmoxDriver.egg-info/requires.txt
ProxmoxDriver.egg-info/top_level.txt
proxmoxdriver/__init__.py
proxmoxdriver/proxmoxdriver.py