Metadata-Version: 1.0
Name: ProxmoxDriver
Version: 0.1.0
Summary: Driver for communicating with a proxmox API.
Home-page: https://github.com/m-o-n-k/ProxmoxDriver
Author: Thomas Steinert
Author-email: monk@10forge.org
License: MIT
Platform: UNKNOWN
